odoo/addons/ssi_letter/README.rst
odoo/addons/ssi_letter/__init__.py
odoo/addons/ssi_letter/__manifest__.py
odoo/addons/ssi_letter/menu.xml
odoo/addons/ssi_letter/data/approval_template_data.xml
odoo/addons/ssi_letter/data/ir_sequence_data.xml
odoo/addons/ssi_letter/data/policy_template_data.xml
odoo/addons/ssi_letter/data/sequence_template_data.xml
odoo/addons/ssi_letter/models/__init__.py
odoo/addons/ssi_letter/models/incoming_letter.py
odoo/addons/ssi_letter/models/letter_mixin.py
odoo/addons/ssi_letter/models/letter_type.py
odoo/addons/ssi_letter/models/outgoing_letter.py
odoo/addons/ssi_letter/security/ir.model.access.csv
odoo/addons/ssi_letter/security/ir_module_category_data.xml
odoo/addons/ssi_letter/security/ir_rule_data.xml
odoo/addons/ssi_letter/security/res_group_data.xml
odoo/addons/ssi_letter/static/description/icon.png
odoo/addons/ssi_letter/views/incoming_letter_views.xml
odoo/addons/ssi_letter/views/letter_mixin_views.xml
odoo/addons/ssi_letter/views/letter_type_views.xml
odoo/addons/ssi_letter/views/outgoing_letter_views.xml
odoo14_addon_ssi_letter-14.0.1.1.0.dist-info/METADATA
odoo14_addon_ssi_letter-14.0.1.1.0.dist-info/WHEEL
odoo14_addon_ssi_letter-14.0.1.1.0.dist-info/top_level.txt
odoo14_addon_ssi_letter-14.0.1.1.0.dist-info/RECORD
